m3_adapter_client/__init__.py
m3_adapter_client/actions.py
m3_adapter_client/app_meta.py
m3_adapter_client/apps.py
m3_adapter_client/permissions.py
m3_adapter_client/ui.py
m3_adapter_client-1.2.0.dist-info/METADATA
m3_adapter_client-1.2.0.dist-info/WHEEL
m3_adapter_client-1.2.0.dist-info/dependency_links.txt
m3_adapter_client-1.2.0.dist-info/top_level.txt
m3_adapter_client-1.2.0.dist-info/RECORD
